calculate_savings.py
calculate_savings-0.1.4.dist-info/METADATA
calculate_savings-0.1.4.dist-info/WHEEL
calculate_savings-0.1.4.dist-info/entry_points.txt
calculate_savings-0.1.4.dist-info/top_level.txt
calculate_savings-0.1.4.dist-info/RECORD
